dsnd_distributions_nr
