Metadata-Version: 1.0
Name: dsnd-distributions-nr
Version: 0.2
Summary: Gaussian and binomial distributions
Home-page: UNKNOWN
Author: Nils Randau
Author-email: UNKNOWN
License: UNKNOWN
Platform: UNKNOWN
